glowprom/__init__.py
glowprom/arguments.py
glowprom/cloud_message.py
glowprom/exceptions.py
glowprom/local_message.py
glowprom/mqtt.py
glowprom/server.py
glowprom-0.7.2.data/scripts/glowprom
tests/__init__.py
tests/test_arguments.py
tests/test_cloud_message.py
tests/test_local_message.py
tests/test_mqtt.py
tests/test_server.py
glowprom-0.7.2.dist-info/LICENSE
glowprom-0.7.2.dist-info/METADATA
glowprom-0.7.2.dist-info/WHEEL
glowprom-0.7.2.dist-info/top_level.txt
glowprom-0.7.2.dist-info/RECORD
