Metadata-Version: 2.1
Name: glowprom
Version: 0.7.2
Summary: Receives gas and electric meter data from https://glowmarkt.com/ and exposes it to Prometheus.
Home-page: https://github.com/andrewjw/glowprom
Author: Andrew Wilkinson
Author-email: andrewjwilkinson@gmail.com
Classifier: Programming Language :: Python :: 3.8
Classifier: Programming Language :: Python :: 3.9
Classifier: Programming Language :: Python :: 3.10
Classifier: Programming Language :: Python :: 3.11
Classifier: Programming Language :: Python :: 3.12
Classifier: License :: OSI Approved :: GNU General Public License v3 (GPLv3)
Classifier: Operating System :: OS Independent
Requires-Python: >=3.8
License-File: LICENSE
Requires-Dist: paho-mqtt ==2.1.0
Requires-Dist: pycodestyle ==2.12.0
Requires-Dist: coveralls ==4.0.1
Requires-Dist: python-semantic-release ==9.8.3
Requires-Dist: packaging ==24.1
Requires-Dist: wheel ==0.43.0
Requires-Dist: twine ==5.1.1
